MANIFEST.in
README.rst
setup.py
alerts/__init__.py
alerts/admin.py
alerts/forms.py
alerts/helpers.py
alerts/managers.py
alerts/models.py
alerts/utils.py
alerts/migrations/0001_initial.py
alerts/migrations/0002_auto__add_field_alert_context.py
alerts/migrations/__init__.py
alerts/templatetags/__init__.py
alerts/templatetags/alerts.py
django_alerts.egg-info/PKG-INFO
django_alerts.egg-info/SOURCES.txt
django_alerts.egg-info/dependency_links.txt
django_alerts.egg-info/requires.txt
django_alerts.egg-info/top_level.txt