Metadata-Version: 1.1
Name: django-alerts
Version: 0.5.1
Summary: Django alerts
Home-page: https://github.com/PragmaticMates/django-alerts
Author: Pragmatic Mates
Author-email: info@pragmaticmates.com
License: BSD License
Keywords: django alerts notifications
Platform: UNKNOWN
Classifier: Programming Language :: Python
Classifier: Programming Language :: Python :: 2.5
Classifier: Programming Language :: Python :: 2.6
Classifier: Programming Language :: Python :: 2.7
Classifier: Operating System :: OS Independent
Classifier: Environment :: Web Environment
Classifier: Intended Audience :: Developers
Classifier: Framework :: Django
Classifier: License :: OSI Approved :: BSD License
Classifier: Development Status :: 3 - Alpha
